<FIXML xsi:schemaLocation="http://www.finacle.com/fixml SBAcctAdd.xsd" xmlns="http://www.finacle.com/fixml" xmlns:xsi="http://www.w3.org/2001/XMLSchema-instance">

<Header>

<RequestHeader>

<MessageKey>

<RequestUUID>TAB_1017687408yree328y940791</RequestUUID>

<ServiceRequestId>SBAcctAdd</ServiceRequestId>

<ServiceRequestVersion>10.2</ServiceRequestVersion>

<ChannelId>TA2</ChannelId>

<LanguageId>

</LanguageId>

</MessageKey>

<RequestMessageInfo>

<BankId>

</BankId>

<TimeZone>

</TimeZone>

<EntityId>

</EntityId>

<EntityType>

</EntityType>

<ArmCorrelationId>

</ArmCorrelationId>

<MessageDateTime>2020-09-17T16:52:59.147</MessageDateTime>

</RequestMessageInfo>

<Security>

<Token>

<PasswordToken>

<UserId>

</UserId>

<Password>

</Password>

</PasswordToken>

</Token>

<FICertToken>

</FICertToken>

<RealUserLoginSessionId>

</RealUserLoginSessionId>

<RealUser>

</RealUser>

<RealUserPwd>

</RealUserPwd>

<SSOTransferToken>

</SSOTransferToken>

</Security>

</RequestHeader>

</Header>

<Body>

<SBAcctAddRequest>

<SBAcctAddRq>

<CustId>

<CustId>40223911</CustId>

</CustId>

<SBAcctId>

<AcctId></AcctId>

<AcctType>

<SchmCode>SBMIC</SchmCode>

<SchmType>SBA</SchmType>

</AcctType>

<AcctCurr>INR</AcctCurr>

</SBAcctId>

<SBAcctGenInfo>

<GenLedgerSubHead>

<GenLedgerSubHeadCode>35095</GenLedgerSubHeadCode>

<CurCode>INR</CurCode>

</GenLedgerSubHead>

<AcctName>HARINDER KUMAR</AcctName>

<AcctShortName>HARINDERKU</AcctShortName>

<AcctStmtMode>B</AcctStmtMode>

<AcctStmtFreq>

<SOURCE_CODE>B30700</SOURCE_CODE>

<MOB_NUMBER1>9346563949</MOB_NUMBER1>

<MOTHER_MAIDEN_NAME>jamuna</MOTHER_MAIDEN_NAME>

<EMAIL_ID></EMAIL_ID>

<Cal>00</Cal>

<Type>Q</Type>

<StartDt>31</StartDt>

<WeekDay>

</WeekDay>

<WeekNum>

</WeekNum>

<HolStat>P</HolStat>

<AcctStmtNxtPrintDt>2022-12-17T16:52:59.147</AcctStmtNxtPrintDt></AcctStmtFreq>



<DespatchMode>C</DespatchMode>

</SBAcctGenInfo>

<NomineeInfoRec>

<RegNum>6914456256</RegNum>

<NomineeName>pavan</NomineeName>

<RelType>BRO</RelType>

<NomineeContactInfo>

<PostAddr>

<Addr1>Hno 4-65,Porumalla,Medipelli Mandal</Addr1>

<Addr2>Medipelli MandalPormalla,Karimnagar,Andhra Pr</Addr2>

<City>SEC</City>

<StateProv>ADH</StateProv>

<PostalCode>505453</PostalCode>

<Country>IN</Country>

</PostAddr>

</NomineeContactInfo>

<NomineeMinorFlg>N</NomineeMinorFlg>

<NomineePercent>

<value>100</value>

</NomineePercent>

</NomineeInfoRec>

</SBAcctAddRq>

<SBAcctAdd_CustomData>

<INTCRACCTFLG>S</INTCRACCTFLG>

<SOL>0520</SOL>

<INTDRACCTFLG>S</INTDRACCTFLG>

<CAL>N</CAL>

<SOURCE_CODE>B30700</SOURCE_CODE>

<MOB_NUMBER1>9346563949</MOB_NUMBER1>

<MOTHER_MAIDEN_NAME>jamuna</MOTHER_MAIDEN_NAME>

<FREE_CODE_4>TAB2</FREE_CODE_4>

<FREE_CODE_8></FREE_CODE_8>

<FREE_CODE_10>OD</FREE_CODE_10>

<APPLN_REF_NUM>6914456256</APPLN_REF_NUM>

<MISCFLG>1</MISCFLG>

<FREZ_CODE>D</FREZ_CODE>

<FREZ_REASON_CODE>067</FREZ_REASON_CODE>

<LAST_FREZ_DATE>17-09-2021</LAST_FREZ_DATE>

<CR_INT_TYPE>Q</CR_INT_TYPE>

<CR_INT_WEEK_DAY>0</CR_INT_WEEK_DAY>

<CR_INT_START_DT>31</CR_INT_START_DT>

<CR_INT_HOL_ST>P</CR_INT_HOL_ST>

<CR_INT_CAL_TYPE>00</CR_INT_CAL_TYPE>

<CR_INT_NXT_RUN_DT>30-12-2022</CR_INT_NXT_RUN_DT>

<DR_INT_TYPE>Q</DR_INT_TYPE>

<DR_INT_WEEK_DAY>0</DR_INT_WEEK_DAY>

<DR_INT_START_DT>31</DR_INT_START_DT>

<DR_INT_HOL_ST>P</DR_INT_HOL_ST>

<DR_INT_CAL_TYPE>00</DR_INT_CAL_TYPE>

<DR_INT_NXT_RUN_DT>30-12-2022</DR_INT_NXT_RUN_DT>

<MODE_OF_OPR>009</MODE_OF_OPR>

<INTCRACCTFLGCODE>S</INTCRACCTFLGCODE>

<INTDRACCTFLGCODE>S</INTDRACCTFLGCODE>

<CR_NXT_INT_DATE>2022-12-30T00:00:00.000</CR_NXT_INT_DATE>

<DR_NXT_INT_DATE>2022-11-23T00:00:00.000</DR_NXT_INT_DATE>

<STRUSERFIELD23>PAN</STRUSERFIELD23>

<STRUSERFIELD24>ASVPL1865D</STRUSERFIELD24>

<ECS>Y</ECS>

</SBAcctAdd_CustomData>

</SBAcctAddRequest>

</Body>

</FIXML>